alcor_cyclope/__init__.py
alcor_cyclope/cli.py
alcor_cyclope/client.py
alcor_cyclope-0.1.3.dist-info/LICENSE
alcor_cyclope-0.1.3.dist-info/METADATA
alcor_cyclope-0.1.3.dist-info/WHEEL
alcor_cyclope-0.1.3.dist-info/entry_points.txt
alcor_cyclope-0.1.3.dist-info/top_level.txt
alcor_cyclope-0.1.3.dist-info/RECORD
