Metadata-Version: 2.2
Name: alcor_cyclope
Version: 0.1.3
Summary: Client for interacting with the Alcor Cyclope seeing monitor TCP API
Author-email: Dale Ghent <daleg@elemental.org>
License: MIT
Classifier: Programming Language :: Python :: 3
Classifier: Operating System :: OS Independent
Classifier: License :: OSI Approved :: MIT License
Classifier: Topic :: Scientific/Engineering :: Astronomy
Classifier: Topic :: Scientific/Engineering :: Atmospheric Science
Requires-Python: >=3.10
License-File: LICENSE
